django_mysql_fuzzycount-0.4.dist-info/METADATA
django_mysql_fuzzycount-0.4.dist-info/RECORD
django_mysql_fuzzycount-0.4.dist-info/WHEEL
django_mysql_fuzzycount-0.4.dist-info/top_level.txt
mysql_fuzzycount/__init__.py
mysql_fuzzycount/admin.py
mysql_fuzzycount/managers.py
mysql_fuzzycount/models.py
mysql_fuzzycount/queryset.py
