Metadata-Version: 2.1
Name: django-mysql-fuzzycount
Version: 0.4
Summary: Approximate query counts for MySQL and Django.
Home-page: https://github.com/educreations/django-mysql-fuzzycount
Author: Chris Streeter
Author-email: chris@educreations.com
License: MIT
Keywords: mysql orm django
Platform: UNKNOWN
Classifier: Intended Audience :: Developers
Classifier: Operating System :: OS Independent
Classifier: Programming Language :: Python
Classifier: Environment :: Web Environment
Classifier: Framework :: Django
Classifier: License :: OSI Approved :: MIT License
Classifier: Programming Language :: Python :: 2.7
Classifier: Topic :: Software Development
Requires-Dist: django (>=1.6)
Requires-Dist: django-model-utils (>=1.4.0)
